{
  "O": 0,
  "S-CARDINAL": 1,
  "B-PERSON": 2,
  "S-TIME": 3,
  "S-PERSON": 4,
  "B-DATE": 5,
  "B-LAW": 6,
  "B-LOC": 7,
  "B-WORK_OF_ART": 8,
  "S-GPE": 9,
  "S-NORP": 10,
  "B-CARDINAL": 11,
  "S-ORG": 12,
  "B-PERCENT": 13,
  "S-ORDINAL": 14,
  "B-ORG": 15,
  "B-GPE": 16,
  "S-WORK_OF_ART": 17,
  "B-TIME": 18,
  "S-PRODUCT": 19,
  "S-DATE": 20,
  "S-FAC": 21,
  "B-FAC": 22,
  "B-EVENT": 23,
  "B-MONEY": 24,
  "B-QUANTITY": 25,
  "S-LANGUAGE": 26,
  "S-QUANTITY": 27,
  "B-NORP": 28,
  "S-LOC": 29,
  "B-PRODUCT": 30,
  "S-EVENT": 31,
  "<GO>": 32,
  "<EOS>": 33,
  "S-LAW": 34,
  "B-ORDINAL": 35,
  "S-MONEY": 36,
  "B-LANGUAGE": 37,
  "S-PERCENT": 38,
  "E-PERSON": 39,
  "I-PERSON": 40,
  "I-LAW": 41,
  "E-LAW": 42,
  "I-DATE": 43,
  "E-DATE": 44,
  "I-ORG": 45,
  "E-ORG": 46,
  "E-TIME": 47,
  "I-TIME": 48,
  "I-WORK_OF_ART": 49,
  "E-WORK_OF_ART": 50,
  "E-LOC": 51,
  "I-LOC": 52,
  "E-PERCENT": 53,
  "I-PERCENT": 54,
  "E-CARDINAL": 55,
  "I-CARDINAL": 56,
  "E-GPE": 57,
  "I-GPE": 58,
  "E-QUANTITY": 59,
  "I-QUANTITY": 60,
  "I-MONEY": 61,
  "E-MONEY": 62,
  "I-EVENT": 63,
  "E-EVENT": 64,
  "I-NORP": 65,
  "E-NORP": 66,
  "E-FAC": 67,
  "I-FAC": 68,
  "E-PRODUCT": 69,
  "I-PRODUCT": 70,
  "I-ORDINAL": 71,
  "E-ORDINAL": 72,
  "I-LANGUAGE": 73,
  "E-LANGUAGE": 74
}